{
  "name": "크립토",
  "source": "TLDR Crypto",
  "icon": "🪙",
  "color": "#f6c453",
  "bg": "#332a12",
  "items": [
    {
      "id": "crypto-bitcoin-65k-cpi-miss",
      "title": "비트코인, CPI 서프라이즈로 6만5000달러 회복… 코호트는 매도 지속",
      "summary": "6월 CPI가 예상치를 밑돌며 상승했지만, 장기·단기 보유자 모두 랠리 속에서 매도세를 이어갔다.",
      "source": "CoinDesk",
      "url": "https://www.coindesk.com/markets/2026/07/16/two-groups-of-bitcoin-investors-sell-on-the-rise-as-inflation-lifts-prices-to-nearly-usd65-000?utm_source=tldrcrypto",
      "report": {
        "tldr": "6월 CPI가 전년 대비 3.5%로 컨센서스 3.8%를 밑돌면서 비트코인이 약 6만5000달러까지 올랐지만, 두 보유자 그룹이 랠리 속에서 계속 매도하고 있다.",
        "what": "핵심 CPI는 2.6%를 기록했고 달러지수는 0.5% 하락한 100.48을 나타냈다. 온체인 데이터를 보면 2025년 고점 부근에서 매입한 장기 보유자(5개월 이상)들은 6만달러 아래에서보다 좁은 마진으로 손실을 실현 중이고, 최근 저점 부근에서 매집한 단기 보유자들은 하루 400만달러 이상 속도로 물량을 풀고 있어 5월 8만2000달러 반등 당시와 비슷한 속도다. 비트겟의 라이언 리는 이번 CPI 수치가 이미 반전된 유가 흐름 속에서 10% 급락한 휘발유 가격이 견인한 것이어서 '오래된 신호'일 수 있다고 지적했고, 윈터뮤트의 재스퍼 드 매러는 군사적 긴장이 이어지는 가운데 한 번의 CPI 서프라이즈만으로 거시 국면 전환을 단정할 수 없다고 덧붙였다.",
        "points": [
          "6월 CPI 3.5% YoY(컨센서스 3.8%), 근원 CPI 2.6%",
          "비트코인 약 6만5000달러, 달러지수 100.48로 0.5% 하락",
          "장기 보유자는 좁은 마진으로 손실 실현 중",
          "단기 보유자는 하루 400만달러 이상 속도로 매도",
          "전문가들은 CPI 서프라이즈 하나로 거시 전환 단정은 이르다고 평가"
        ],
        "why": [
          "물가 지표 하나에도 온체인 보유자 행동이 민감하게 반응하며 랠리 지속 가능성에 의문이 제기됨"
        ]
      }
    },
    {
      "id": "crypto-strategy-secure-until-8k-btc",
      "title": "스트래티지 CEO \"비트코인 8000달러까지는 안전\"… 균열 신호도 포착",
      "summary": "우선주 STRC가 액면가 아래로 떨어지고 mNAV가 압축되며 매집 플라이휠에 제동이 걸렸다.",
      "source": "CoinDesk",
      "url": "https://www.coindesk.com/markets/2026/07/15/strategy-feels-very-secure-until-bitcoin-reaches-usd8-000-usd10-000-says-ceo?utm_source=tldrcrypto",
      "report": {
        "tldr": "스트래티지 CEO 퐁 레는 비트코인이 현재가 6만4500달러에서 약 85% 하락한 8000~1만달러 구간까지 가지 않는 한 회사 재무상태가 안전하다고 밝혔다.",
        "what": "그러나 이런 낙관과 배치되는 두 가지 구조적 스트레스 신호가 있다. 우선주 STRC가 액면가 100달러 아래, 75달러 미만으로 떨어져 비트코인 매입을 위한 신규 주식 발행이 제약됐고, 회사의 mNAV(주가순자산배수)는 1.02로 압축돼 주식-비트코인 매집 플라이휠을 지탱하던 프리미엄이 사라졌다. MSTR 주가는 이날 거의 6% 하락했고 지난 1년간 78% 떨어졌다. 레 CEO가 달러 유동성 확보를 강조한 것은 자본시장을 통한 지속적 비트코인 매집이라는 기존 기조에서의 전술적 전환을 뜻한다.",
        "points": [
          "CEO: 비트코인 8000~1만달러까지는 재무 안전 주장",
          "우선주 STRC 액면가 100달러 아래, 75달러 미만으로 하락",
          "mNAV 1.02로 압축, 매집 플라이휠 프리미엄 소멸",
          "MSTR 주가 당일 약 6% 하락, 1년간 78% 하락",
          "CEO, 달러 유동성 확보로 전술 전환 시사"
        ],
        "why": [
          "비트코인 매집 전략을 표방한 상장사의 재무 구조적 취약점이 드러나고 있음"
        ]
      }
    },
    {
      "id": "crypto-arc-deleted-mempool",
      "title": "서클의 'Arc', 멤풀을 없애다… 아무도 눈치채지 못한 변화",
      "summary": "멀티프로포저 프로토콜로 프런트러닝을 원천 차단, 초당 3000건·서브350ms 파이널리티를 구현했다.",
      "source": "Thread Reader",
      "url": "https://threadreaderapp.com/thread/2077505550057881951.html?utm_source=tldrcrypto",
      "report": {
        "tldr": "서클이 5월 공개한 arXiv 논문은 대기 중인 트랜잭션을 프런트러닝 봇에 노출시키는 공개 멤풀을 없애는 Arc의 멀티프로포저 프로토콜(AMP)을 설명한다.",
        "what": "블록 빌더가 거래를 재정렬해 이익을 취하는 대신, 전담 프로포저가 거래를 검증자에게 직접 전달하며 포함이 보장된다. 말라카이트 BFT 합의 엔진 위에 구축된 Arc의 테스트넷은 2025년 10월 이후 2억4400만건 이상의 거래를 처리했고, 초당 약 3000건 처리량과 350밀리초 미만의 파이널리티를 기록했다. 변동성 있는 자체 토큰이 아닌 USDC로 가스비를 부과하며, 이번 여름 양자내성 서명을 갖춘 채로 메인넷 출시가 예정돼 있다.",
        "points": [
          "멀티프로포저 프로토콜(AMP)로 공개 멤풀 제거",
          "말라카이트 BFT 합의 엔진 기반",
          "테스트넷 누적 처리 2억4400만건 이상(2025년 10월 이후)",
          "초당 약 3000건, 파이널리티 350ms 미만",
          "가스비는 USDC로 지불, 양자내성 서명 갖춰 이번 여름 메인넷 출시 예정"
        ],
        "why": [
          "프런트러닝의 근본 원인인 공개 멤풀 자체를 제거하는 설계는 체인 구조 차원의 접근"
        ]
      }
    },
    {
      "id": "crypto-fynd-flashblocks-base",
      "title": "'핀드', 베이스 플래시블록 실시간 대응으로 propAMM 차익거래 무력화",
      "summary": "200ms마다 갱신되는 블록 상태 지연을 이용한 propAMM 전략이 97.4%의 확률로 작동했음이 드러났다.",
      "source": "TLDR Crypto",
      "url": "https://links.tldrnewsletter.com/XS5Nxe",
      "report": {
        "tldr": "베이스의 플래시블록 아키텍처는 200ms마다 새로운 블록 상태를 만들어내지만, 대부분의 DEX 애그리게이터는 250ms 이상 걸리는 RPC 호출에 의존해 최대 15초까지 상태가 뒤처질 수 있다.",
        "what": "propAMM은 이 격차를 이용해 블록 N의 마지막 플래시블록에서 경쟁력 있는 가격을 제시한 뒤 블록 N+1 시작 시점에 스프레드를 넓히는 방식으로 이익을 취한다. 0x가 461개 블록을 분석한 결과 이 패턴이 97.4% 확률로 발생했고 거래당 5~10bp의 비용을 유발했다. 프로펠러헤즈의 로컬 배포형 라우터 '핀드'는 플래시블록 델타를 인메모리 상태로 스트리밍해 매 견적이 이전 블록이 아닌 현재 상태를 반영하도록 만들어, propAMM이 핀드가 어떤 플래시블록 상태로 라우팅할지 예측하지 못하게 하고 10건 중 9건에서 propAMM의 예측을 빗나가게 만든다. 로컬 배포는 외부 애그리게이터 API의 약 500ms 왕복 지연도 제거한다.",
        "points": [
          "베이스 플래시블록, 200ms마다 새 블록 상태 생성",
          "일반 애그리게이터는 최대 15초까지 상태 지연 가능",
          "0x 분석: propAMM 차익거래 패턴 97.4% 발생, 거래당 5~10bp 비용",
          "핀드는 플래시블록 델타를 인메모리 스트리밍으로 실시간 반영",
          "핀드 도입 후 propAMM 예측이 10건 중 9건 빗나감"
        ],
        "why": [
          "블록체인 인프라 레이어의 미세한 지연 격차가 실제 트레이더 비용으로 직결됨을 정량적으로 보여줌"
        ]
      }
    },
    {
      "id": "crypto-cold-storage-multisig-guide",
      "title": "\"하드웨어 지갑이 안전하지 않다\"는 지적에 대한 콜드스토리지 멀티시그 대응법",
      "summary": "2-of-3 세이프 멀티시그로 고액 크립토 자산을 보호하는 실전 가이드가 공유됐다.",
      "source": "Thread Reader",
      "url": "https://threadreaderapp.com/thread/2077518810236830181.html?utm_source=tldrcrypto",
      "report": {
        "tldr": "ZachXBT의 '하드웨어 지갑은 안전하지 않다'는 주장에 대응해, 3개의 독립된 서명 기기를 이용한 2-of-3 세이프 멀티시그 구성법을 소개하는 스레드다.",
        "what": "잠금 처리된 전용 아이폰, 별도 폰이나 하드웨어 지갑, 오프라인 백업 기기 각각이 서명자가 되며 자금 이동에는 셋 중 둘의 승인이 필요하다. 전용 서명 기기에서는 심카드·이메일·소셜 앱을 모두 제거하고, 복구 구문은 종이나 강철판에 오프라인으로 보관하며, 소액 거래로 전체 구성을 먼저 테스트하고, 일상적으로 쓰는 지갑에는 생활비 정도의 금액만 남겨둘 것을 권장한다.",
        "points": [
          "2-of-3 세이프 멀티시그, 독립된 서명 기기 3대 사용",
          "전용 서명 기기는 심카드·이메일·소셜 앱 제거",
          "복구 구문은 종이·강철판에 오프라인 보관",
          "소액 거래로 먼저 테스트, 일상 지갑엔 소액만 유지"
        ],
        "why": [
          "고액 크립토 보유자를 위한 실전 보안 체크리스트 성격의 가이드"
        ],
        "action": "고액 자산을 보유한 경우 2-of-3 멀티시그 구성을 검토하고 서명 기기를 생활 기기와 분리"
      }
    },
    {
      "id": "crypto-robinhood-memecoin-chain-warning",
      "title": "\"로빈후드, 밈코인 체인으로 남지 마라\" 경고",
      "summary": "빠른 초기 성장에도 밈코인 거래 비중이 장기 신뢰도를 위협한다는 지적.",
      "source": "TLDR Crypto",
      "url": "https://links.tldrnewsletter.com/LAulpV",
      "report": {
        "tldr": "로빈후드 체인은 일일 활성 주소 30만개 이상, 일일 현물 DEX 거래량 10억달러 이상(전체 체인 중 2위) 등 강한 초기 성장세를 보였다.",
        "what": "연간 환산 수수료 4000만달러, TVL 3억달러 이상(모르포·에테나·유니스왑 중심)도 기록했지만, 이 DEX 거래량의 대부분은 밈코인 거래에서 나온다. 2024년 초 베이스에서 출시된 밈코인들이 올해 90%, 고점 대비 99% 하락한 전례가 있어 소매 신뢰를 무너뜨리고 로빈후드를 신뢰할 수 있는 금융 인프라가 아닌 GME 시대의 투기적 이미지와 연결시킬 위험이 있다는 지적이다. 대안으로 토큰화 주식, RWA, 예측 시장으로 유동성을 유도하는 방향이 제시됐다. 낙관적 시나리오로는 2030년까지 월간활성이용자 1억명, ARPU 100달러 달성 시 소비자 매출 100억달러로, 현재 애널리스트들의 2029 회계연도 컨센서스(87억8000만달러)를 넘어선다는 전망도 있다.",
        "points": [
          "일일 활성 주소 30만개 이상, 일일 DEX 거래량 10억달러 이상(전체 2위)",
          "연간 환산 수수료 4000만달러, TVL 3억달러 이상",
          "DEX 거래량 대부분이 밈코인 거래",
          "베이스 밈코인 사례: 올해 90%, 고점 대비 99% 하락",
          "대안: 토큰화 주식·RWA·예측 시장으로 유동성 유도",
          "낙관 시나리오: 2030년 MAU 1억명, 소비자 매출 100억달러 전망"
        ],
        "why": [
          "밈코인發 초기 트랙션이 장기적으로는 브랜드 신뢰를 갉아먹을 수 있다는 경고"
        ]
      }
    },
    {
      "id": "crypto-privacy-tokens-best-sector",
      "title": "프라이버시 토큰, 올해 유일하게 오른 크립토 섹터로",
      "summary": "73개 거래소 상장폐지에도 1년간 127.3% 상승, 영지식증명 기반 프라이버시 수요가 배경.",
      "source": "TLDR Crypto",
      "url": "https://links.tldrnewsletter.com/Pc0hX2",
      "report": {
        "tldr": "프라이버시 토큰은 지난 1년간 127.3% 상승하며 이번 사이클 최고 성과 크립토 섹터가 됐다. 2025년 한 해 동안 73개 거래소가 프라이버시 토큰을 상장폐지했음에도 나온 결과다.",
        "what": "이 흐름은 비트코인의 공개 원장이 코인 이력과 지갑 신원을 추적 가능하게 만들면서 대체가능성(fungibility)을 훼손한 데서 비롯됐다는 분석이다. 영지식증명은 송신자·수신자·금액을 노출하지 않고도 네트워크가 거래의 유효성을 검증할 수 있게 해주며, 모네로와 지캐시 같은 프로젝트는 각국 정부가 상충하는 규제를 밀어붙이는 가운데 컴플라이언스 관련 노선이 갈리고 있다.",
        "points": [
          "1년간 127.3% 상승, 이번 사이클 최고 성과 섹터",
          "2025년 73개 거래소가 프라이버시 토큰 상장폐지",
          "영지식증명으로 송신자·수신자·금액 비공개 검증 가능",
          "모네로·지캐시 등이 각국 규제 대응에서 노선 분화"
        ],
        "why": [
          "규제 압박 속에서도 프라이버시에 대한 시장 수요가 오히려 강화되고 있음을 보여줌"
        ]
      }
    },
    {
      "id": "crypto-visa-stablecoin-micro-commerce",
      "title": "비자 \"스테이블코인이 AI 에이전트 경제의 마이크로커머스를 구동할 것\"",
      "summary": "카드 레일과 스테이블코인 결제가 매크로·마이크로 커머스로 역할 분담할 전망.",
      "source": "TLDR Crypto",
      "url": "https://links.tldrnewsletter.com/AfjesQ",
      "report": {
        "tldr": "비자는 AI 에이전트 커머스가 매크로커머스(여행 예약 등 소비자 규모 구매, 카드 레일에 적합)와 마이크로커머스(소프트웨어 시스템 간 빈번한 소액 결제, 저비용 스테이블코인 결제가 유리)로 나뉠 것으로 내다봤다.",
        "what": "비자는 자사의 비자 인텔리전트 커머스 같은 카드 네이티브 프로토콜이 스테이블코인 지원을 추가하고, 크립토 네이티브 프로토콜은 전통적 신뢰 인프라를 채택하는 하이브리드 모델을 예상한다. 다만 기존 법률 체계와 차지백 시스템이 인간의 직접 판단 없이 거래하는 자율 에이전트를 염두에 두고 설계되지 않았다는 점도 인정했다.",
        "points": [
          "매크로커머스: 소비자 규모 구매, 카드 레일 적합",
          "마이크로커머스: 소액·고빈도 결제, 스테이블코인 적합",
          "카드 네이티브·크립토 네이티브 프로토콜의 하이브리드 모델 예상",
          "기존 법·차지백 체계는 자율 에이전트 거래에 미대응"
        ],
        "why": [
          "AI 에이전트 경제가 확산되면서 결제 인프라의 역할 분담 구도가 구체화되고 있음"
        ]
      }
    },
    {
      "id": "crypto-defillama-mica-onramp-offramp",
      "title": "디파이라마, MiCA 대시보드에 온·오프램프 비용 추적 추가",
      "summary": "SEPA 수수료·테이커 수수료·슬리피지까지 유로-비트코인 전환 총비용을 분해해 보여준다.",
      "source": "Thread Reader",
      "url": "https://threadreaderapp.com/thread/2077665035569029246.html?utm_source=tldrcrypto",
      "report": {
        "tldr": "디파이라마가 MiCA 대시보드에 온램프·오프램프 비용 추적 기능을 추가했다.",
        "what": "유로를 비트코인으로, 다시 비트코인을 유로로 전환하는 전 과정의 총비용을 SEPA 이체 수수료, 테이커 수수료, 슬리피지, 네트워크 출금 수수료까지 세분화해 보여준다.",
        "points": [
          "온램프·오프램프 총비용을 항목별로 분해",
          "SEPA 이체 수수료·테이커 수수료·슬리피지·네트워크 수수료 포함"
        ],
        "why": [
          "유럽 MiCA 규제 환경에서 크립토 전환 비용의 투명성을 높이는 도구"
        ]
      }
    },
    {
      "id": "crypto-stanford-polymarket-manipulation",
      "title": "스탠퍼드 연구, 폴리마켓 5분 BTC 마켓 조작 정황 포착",
      "summary": "의심 조작자 821명이 정산 직전 집중 거래로 820만달러를 챙긴 것으로 추정된다.",
      "source": "Thread Reader",
      "url": "https://threadreaderapp.com/thread/2077608393116877057.html?utm_source=tldrcrypto",
      "report": {
        "tldr": "스탠퍼드대와 싱가포르경영대 연구진이 폴리마켓의 5분 비트코인 마켓에서 821명의 의심 조작자를 발견했다.",
        "what": "이들은 정산 직전 마지막 몇 초 동안 집중된 거래를 배치해 비트코인 가격을 순간적으로 움직인 뒤 반전시키는 방식으로 총 820만달러를 챙긴 것으로 추정된다.",
        "points": [
          "의심 조작자 821명 확인",
          "정산 직전 집중 거래로 가격 순간 조작",
          "추정 수익 820만달러"
        ],
        "why": [
          "초단기 예측 시장 구조 자체가 가격 조작에 취약할 수 있음을 학술적으로 입증"
        ]
      }
    },
    {
      "id": "crypto-coinbase-stablecoin-bank-deposits",
      "title": "코인베이스 연구소 \"스테이블코인, 소형은행 예금에 위협 안 돼\"",
      "summary": "USDC 성장률이 은행 요구불예금 성장률과 거의 동일하게 나타났다.",
      "source": "Thread Reader",
      "url": "https://threadreaderapp.com/thread/2077718147184898334.html?utm_source=tldrcrypto",
      "report": {
        "tldr": "코인베이스 연구소의 새 보고서는 스테이블코인 성장과 은행 예금 수준 사이에 의미 있는 연관성이 없다고 결론지었다.",
        "what": "지난 6개월간 USDC는 4.6% 성장했고, 같은 기간 전체 요구불예금은 4.5% 성장해 거의 비슷한 흐름을 보였다.",
        "points": [
          "USDC 6개월 성장률 4.6%",
          "요구불예금 6개월 성장률 4.5%",
          "두 지표 간 뚜렷한 상관관계 없음"
        ],
        "why": [
          "스테이블코인이 은행 시스템에서 예금을 유출시킬 것이라는 우려에 대한 반증 데이터"
        ]
      }
    },
    {
      "id": "crypto-senate-opposes-sbf-clemency",
      "title": "美 상원, SBF 사면 만장일치 반대 결의",
      "summary": "샘 뱅크먼-프리드의 감형 시도에 상원이 초당적으로 제동을 걸었다.",
      "source": "Thread Reader",
      "url": "https://threadreaderapp.com/thread/2077655219236913291.html?utm_source=tldrcrypto",
      "report": {
        "tldr": "미국 상원이 만장일치 동의로, 샘 뱅크먼-프리드(SBF)가 대통령 사면이나 형기 단축 등 어떤 형태의 연방 감형도 받아서는 안 된다는 비구속적 결의안을 통과시켰다.",
        "what": "이는 SBF가 감형을 모색해온 노력과, 트럼프 대통령이 앞서 바이낸스 창립자 창펑자오와 실크로드 창립자 로스 울브리히트를 사면한 전례에 이어 나왔다.",
        "points": [
          "상원 만장일치 동의로 비구속적 결의안 통과",
          "SBF의 감형 시도에 대응한 조치",
          "앞서 창펑자오·로스 울브리히트 사면 전례 존재"
        ],
        "why": [
          "크립토 업계 최대 사기 사건에 대한 정치권의 초당적 강경 기조를 재확인"
        ]
      }
    }
  ]
}